iex/__init__.py
iex/iex.py
python_iex-0.1.0.dist-info/METADATA
python_iex-0.1.0.dist-info/RECORD
python_iex-0.1.0.dist-info/WHEEL
python_iex-0.1.0.dist-info/top_level.txt
