Metadata-Version: 2.1
Name: python-iex
Version: 0.1.0
Summary: A package for communicating with the IEX API.
Home-page: https://github.com/alexmcdonald1124/python-iex
Author: Alexander McDonald
Author-email: alexmcdonald1124@gmail.com
License: UNKNOWN
Platform: UNKNOWN
Classifier: Development Status :: 2 - Pre-Alpha
Classifier: Programming Language :: Python
Classifier: Programming Language :: Python :: 2
Classifier: Programming Language :: Python :: 2.7
Classifier: Programming Language :: Python :: 3
Classifier: Programming Language :: Python :: 3.4
Classifier: Programming Language :: Python :: 3.5
Classifier: Programming Language :: Python :: 3.6
Classifier: Programming Language :: Python :: 3.7
Requires-Dist: requests
